Anilist/__init__.py
Anilist/anilist_types.py
Anilist/auth/__init__.py
Anilist/auth/auth.py
Anilist/auth/code.py
Anilist/auth/token.py
Anilist/client/__init__.py
Anilist/client/client.py
Anilist/client/mutation.py
Anilist/client/query.py
Anilist/errors/__init__.py
Anilist/errors/request.py
Anilist/mutation/__init__.py
Anilist/mutation/media_list.py
Anilist/mutation/mutable.py
Anilist/query/__init__.py
Anilist/query/media_entry.py
Anilist/query/media_list.py
Anilist/query/query.py
Anilist/scheme/__init__.py
Anilist/scheme/media_scheme.py
Anilist/scheme/scheme.py
Anilist/utils/__init__.py
Anilist/utils/consts.py
Anilist/utils/logging.py
Anilist/utils/object.py
Anilist/vars/__init__.py
Anilist/vars/vars.py
Anilist-0.9.1.dist-info/LICENSE
Anilist-0.9.1.dist-info/METADATA
Anilist-0.9.1.dist-info/WHEEL
Anilist-0.9.1.dist-info/top_level.txt
Anilist-0.9.1.dist-info/RECORD
