Metadata-Version: 2.1
Name: Anilist
Version: 0.9.1
Summary: Anilist API wrapper
Author-email: Ann Mauduy-Decius <ann.mauduy.decius@gmail.com>
Project-URL: Homepage, https://github.com/xxxAnn/Anilist.py
Project-URL: Bug Tracker, https://github.com/xxxAnn/Anilist.py/issues
Classifier: Programming Language :: Python :: 3
Classifier: License :: OSI Approved :: MIT License
Classifier: Operating System :: OS Independent
Requires-Python: >=3.10
License-File: LICENSE
